cerebras/appliance/__init__.py
cerebras/appliance/_version.py
cerebras/appliance/appliance_client.py
cerebras/appliance/appliance_manager.py
cerebras/appliance/cluster_config.py
cerebras/appliance/environment.py
cerebras/appliance/errors.py
cerebras/appliance/log.py
cerebras/appliance/bin/raw/README.md
cerebras/appliance/bin/raw/csctl
cerebras/appliance/cluster/__init__.py
cerebras/appliance/cluster/client.py
cerebras/appliance/cluster/cluster_details.py
cerebras/appliance/cluster/config.py
cerebras/appliance/cluster/job_timer.py
cerebras/appliance/cluster/mount_volume.py
cerebras/appliance/cluster/surrogate_job.py
cerebras/appliance/cluster/surrogate_script.py
cerebras/appliance/cluster/types.py
cerebras/appliance/data/__init__.py
cerebras/appliance/data/conversions.py
cerebras/appliance/data/dtypes.py
cerebras/appliance/pb/__init__.py
cerebras/appliance/pb/common/__init__.py
cerebras/appliance/pb/common/diagnostic_pb2.py
cerebras/appliance/pb/framework/__init__.py
cerebras/appliance/pb/framework/appliance_service_pb2.py
cerebras/appliance/pb/framework/appliance_service_pb2_grpc.py
cerebras/appliance/pb/hostio/__init__.py
cerebras/appliance/pb/hostio/br_node_config_pb2.py
cerebras/appliance/pb/perfetto/__init__.py
cerebras/appliance/pb/perfetto/perfetto_trace_pb2.py
cerebras/appliance/pb/sdk/__init__.py
cerebras/appliance/pb/sdk/sdk_appliance_pb2.py
cerebras/appliance/pb/sdk/sdk_appliance_pb2_grpc.py
cerebras/appliance/pb/sdk/sdk_common_pb2.py
cerebras/appliance/pb/sdk/sdk_common_pb2_grpc.py
cerebras/appliance/pb/workflow/__init__.py
cerebras/appliance/pb/workflow/appliance/__init__.py
cerebras/appliance/pb/workflow/appliance/cluster_mgmt/__init__.py
cerebras/appliance/pb/workflow/appliance/cluster_mgmt/cluster_pb2.py
cerebras/appliance/pb/workflow/appliance/cluster_mgmt/cluster_pb2_grpc.py
cerebras/appliance/pb/workflow/appliance/cluster_mgmt/mock_injector_pb2.py
cerebras/appliance/pb/workflow/appliance/cluster_mgmt/mock_injector_pb2_grpc.py
cerebras_appliance-2.7.1.dist-info/LICENSE
cerebras_appliance-2.7.1.dist-info/METADATA
cerebras_appliance-2.7.1.dist-info/WHEEL
cerebras_appliance-2.7.1.dist-info/top_level.txt
cerebras_appliance-2.7.1.dist-info/RECORD
