Metadata-Version: 2.1
Name: cerebras-appliance
Version: 2.7.1
Summary: Base client for Cerebras Wafer Scale Cluster
Home-page: https://cerebras.net/
Author: Cerebras Systems
Author-email: support@cerebras.net
Classifier: Development Status :: 5 - Production/Stable
Classifier: Intended Audience :: Developers
Classifier: Intended Audience :: Science/Research
Classifier: Topic :: Scientific/Engineering :: Artificial Intelligence
Classifier: Topic :: Software Development
Classifier: Topic :: Software Development :: Libraries
Classifier: Topic :: System :: Hardware
Classifier: License :: OSI Approved :: BSD License
Classifier: Programming Language :: Python :: 3
License-File: LICENSE
Requires-Dist: pip (>=21.1.2)
Requires-Dist: numpy (==1.25.0)
Requires-Dist: protobuf (==4.21.12)
Requires-Dist: grpcio (==1.51.1)
Requires-Dist: grpcio-tools (==1.51.1)
Requires-Dist: dill
Requires-Dist: h5py (==3.13.0)
Requires-Dist: hdf5plugin (==5.1.0)
Requires-Dist: PyJWT
Requires-Dist: tblib (==3.0.0)
Requires-Dist: tqdm (>=4.42.1)
Requires-Dist: psutil (>=5.8.0)
Requires-Dist: urllib3 (<2)
Requires-Dist: packaging
Requires-Dist: pyyaml
Requires-Dist: zstandard
